{
    "name": "s_m_FEED_Load_ISS_Extract_File_Auto",
    "properties": {
        "activities": [
            {
                "name": "m_FEED_Load_ISS_Extract_File_Auto",
                "type": "Script",
                "dependsOn": [],
                "policy": {
                    "retry": 0,
                    "retryIntervalInSeconds": 30,
                    "secureOutput": false,
                    "secureInput": false
                },
                "userProperties": [],
                "linkedServiceName": {
                    "referenceName": "ls_SNOWFLAKE_WBMI",
                    "type": "LinkedServiceReference"
                },
                "typeProperties": {
                    "scripts": [
                        {
                            "type": "Query",
                            "text": "WITH\nSQ_ISSCommercialAutoExtract AS (\n\tSELECT\n\t\tISSCommercialAutoExtractId,\n\t\tAuditId,\n\t\tCreatedDate,\n\t\tEDWPremiumMasterCalculationPKId,\n\t\tEDWLossMasterCalculationPKId,\n\t\tTypeBureauCode,\n\t\tBureauLineOfInsurance,\n\t\tBureauCompanyNumber,\n\t\tStateProvinceCode,\n\t\tPremiumMasterRunDate,\n\t\tLossMasterRunDate,\n\t\tPolicyKey,\n\t\tPremiumMasterClassCode,\n\t\tLossMasterClassCode,\n\t\tClaimNumber,\n\t\tClaimantNumber,\n\t\tRiskTerritoryCode,\n\t\tPolicyEffectiveDate,\n\t\tCauseOfLoss,\n\t\tDeductibleAmount,\n\t\tCoverageCode,\n\t\tSublineCode,\n\t\tPackageModificationAdjustmentGroupDescription,\n\t\tPremiumMasterDirectWrittenPremiumAmount,\n\t\tPaidLossAmount,\n\t\tOutstandingLossAmount,\n\t\tPolicyExpirationDate,\n\t\tInceptionToDatePaidLossAmount,\n\t\tClaimantCoverageDetailId,\n\t\tAnnualStatementLineNumber,\n\t\tZipPostalCode,\n\t\tDeductibleIndicatorCode,\n\t\tPolicyLowerLimit,\n\t\tPolicyUpperLimit,\n\t\tTerminalZoneCode,\n\t\tWrittenExposure,\n\t\tPaidAllocatedLossAdjustmentExpenseAmount,\n\t\tOutstandingAllocatedLossAdjustmentExpenseAmount,\n\t\tClaimLossDate,\n\t\tTransactionEffectiveDate,\n\t\tCoverageGroupCode\n\tFROM ISSCommercialAutoExtract\n\tWHERE @{pipeline().parameters.WHERE_CLAUSE}\n),\nEXP_Get_Values AS (\n\tSELECT\n\tISSCommercialAutoExtractId AS WorkISSExtractId,\n\tAuditId,\n\tCreatedDate,\n\tEDWPremiumMasterCalculationPKId,\n\tEDWLossMasterCalculationPKId,\n\tTypeBureauCode,\n\tBureauLineOfInsurance,\n\tBureauCompanyNumber,\n\tStateProvinceCode,\n\tPremiumMasterRunDate,\n\tLossMasterRunDate,\n\tPolicyKey,\n\tPremiumMasterClassCode,\n\tLossMasterClassCode,\n\tClaimNumber,\n\tClaimantNumber,\n\tRiskTerritoryCode,\n\tPolicyEffectiveDate,\n\tCauseOfLoss,\n\tDeductibleAmount,\n\tCoverageCode,\n\tSublineCode,\n\tPackageModificationAdjustmentGroupDescription,\n\tPremiumMasterDirectWrittenPremiumAmount,\n\tPaidLossAmount,\n\tOutstandingLossAmount,\n\tPolicyExpirationDate,\n\tInceptionToDatePaidLossAmount,\n\tClaimantCoverageDetailId,\n\tAnnualStatementLineNumber,\n\tZipPostalCode,\n\tDeductibleIndicatorCode,\n\tPolicyLowerLimit,\n\tPolicyUpperLimit,\n\tTerminalZoneCode,\n\tWrittenExposure,\n\tPaidAllocatedLossAdjustmentExpenseAmount,\n\tOutstandingAllocatedLossAdjustmentExpenseAmount,\n\tClaimLossDate,\n\tTransactionEffectiveDate,\n\tCoverageGroupCode\n\tFROM SQ_ISSCommercialAutoExtract\n),\nRTR_CL_PL AS (\n\tSELECT\n\tWorkISSExtractId,\n\tAuditId,\n\tCreatedDate,\n\tEDWPremiumMasterCalculationPKId,\n\tEDWLossMasterCalculationPKId,\n\tTypeBureauCode,\n\tBureauLineOfInsurance,\n\tBureauCompanyNumber,\n\tStateProvinceCode,\n\tPremiumMasterRunDate,\n\tLossMasterRunDate,\n\tPolicyKey,\n\tPremiumMasterClassCode,\n\tLossMasterClassCode,\n\tClaimNumber,\n\tClaimantNumber,\n\tRiskTerritoryCode,\n\tPolicyEffectiveDate,\n\tCauseOfLoss,\n\tDeductibleAmount,\n\tCoverageCode,\n\tConstructionCode,\n\tISOFireProtectionCode,\n\tSublineCode,\n\tPackageModificationAdjustmentGroupDescription,\n\tPolicyForm,\n\tPremiumMasterDirectWrittenPremiumAmount,\n\tPaidLossAmount,\n\tOutstandingLossAmount,\n\tPolicyExpirationDate,\n\tInceptionToDatePaidLossAmount,\n\tClaimantCoverageDetailId,\n\tAnnualStatementLineNumber,\n\tZipPostalCode,\n\tDeductibleIndicatorCode,\n\tVehicleModelYear,\n\tDefensiveDriverCode,\n\tPolicyLowerLimit,\n\tPolicyUpperLimit,\n\tTerminalZoneCode,\n\tWrittenExposure,\n\tPaidAllocatedLossAdjustmentExpenseAmount,\n\tOutstandingAllocatedLossAdjustmentExpenseAmount,\n\tClaimLossDate,\n\tTransactionEffectiveDate,\n\tCoverageGroupCode\n\tFROM EXP_Get_Values\n),\nRTR_CL_PL_CL AS (SELECT * FROM RTR_CL_PL WHERE IN(TypeBureauCode,'AL','AN','AP','N/A','CommercialAuto')),\nRTR_CL_PL_PL AS (SELECT * FROM RTR_CL_PL WHERE IN(TypeBureauCode,'RL','RN','RP')),\nEXP_Target_CL AS (\n\tSELECT\n\t-- *INF*: TRUNC(SYSDATE,'DD')\n\tCAST(TRUNC(CURRENT_TIMESTAMP, 'DAY') AS TIMESTAMP_NTZ(0)) AS v_RunDate,\n\t-- *INF*: 'ISS_Auto_CL_'||TO_CHAR(v_RunDate,'YYYYMMDD')||'.CSV'\n\t'ISS_Auto_CL_' || TO_CHAR(v_RunDate, 'YYYYMMDD') || '.CSV' AS FileName,\n\tWorkISSExtractId,\n\tAuditId,\n\tCreatedDate,\n\tEDWPremiumMasterCalculationPKId,\n\tEDWLossMasterCalculationPKId,\n\tTypeBureauCode,\n\tBureauLineOfInsurance,\n\tBureauCompanyNumber,\n\tStateProvinceCode,\n\tPremiumMasterRunDate,\n\tLossMasterRunDate,\n\tPolicyKey,\n\tPremiumMasterClassCode,\n\tLossMasterClassCode,\n\tClaimNumber,\n\tClaimantNumber,\n\tRiskTerritoryCode,\n\tPolicyEffectiveDate,\n\tCauseOfLoss,\n\tDeductibleAmount,\n\tCoverageCode,\n\tConstructionCode,\n\tISOFireProtectionCode,\n\tSublineCode,\n\tPackageModificationAdjustmentGroupDescription,\n\tPolicyForm,\n\tPremiumMasterDirectWrittenPremiumAmount,\n\tPaidLossAmount,\n\tOutstandingLossAmount,\n\tPolicyExpirationDate,\n\tInceptionToDatePaidLossAmount,\n\tClaimantCoverageDetailId,\n\tAnnualStatementLineNumber,\n\tZipPostalCode,\n\tDeductibleIndicatorCode,\n\tVehicleModelYear,\n\tDefensiveDriverCode,\n\tPolicyLowerLimit,\n\tPolicyUpperLimit,\n\tTerminalZoneCode,\n\tWrittenExposure,\n\tPaidAllocatedLossAdjustmentExpenseAmount,\n\tOutstandingAllocatedLossAdjustmentExpenseAmount,\n\tClaimLossDate,\n\tTransactionEffectiveDate,\n\tCoverageGroupCode\n\tFROM RTR_CL_PL_CL\n),\nSRT_ISSFlatFile_Auto_CL AS (\n\tSELECT\n\tFileName, \n\tWorkISSExtractId, \n\tAuditId, \n\tCreatedDate, \n\tEDWPremiumMasterCalculationPKId, \n\tEDWLossMasterCalculationPKId, \n\tTypeBureauCode, \n\tBureauLineOfInsurance, \n\tBureauCompanyNumber, \n\tStateProvinceCode, \n\tPremiumMasterRunDate, \n\tLossMasterRunDate, \n\tPolicyKey, \n\tPremiumMasterClassCode, \n\tLossMasterClassCode, \n\tClaimNumber, \n\tClaimantNumber, \n\tRiskTerritoryCode, \n\tPolicyEffectiveDate, \n\tCauseOfLoss, \n\tDeductibleAmount, \n\tCoverageCode, \n\tSublineCode, \n\tPackageModificationAdjustmentGroupDescription, \n\tPremiumMasterDirectWrittenPremiumAmount, \n\tPaidLossAmount, \n\tOutstandingLossAmount, \n\tPolicyExpirationDate, \n\tInceptionToDatePaidLossAmount, \n\tClaimantCoverageDetailId, \n\tAnnualStatementLineNumber, \n\tZipPostalCode, \n\tDeductibleIndicatorCode, \n\tPolicyLowerLimit, \n\tPolicyUpperLimit, \n\tTerminalZoneCode, \n\tWrittenExposure, \n\tPaidAllocatedLossAdjustmentExpenseAmount, \n\tOutstandingAllocatedLossAdjustmentExpenseAmount, \n\tClaimLossDate, \n\tTransactionEffectiveDate, \n\tCoverageGroupCode\n\tFROM EXP_Target_CL\n\tORDER BY PolicyKey ASC, PremiumMasterClassCode ASC, CoverageCode ASC, AnnualStatementLineNumber ASC, ZipPostalCode ASC\n),\nISSFlatFile_Auto_CL AS (\n\tINSERT INTO ISSFlatFile_Auto\n\t(FileName, WorkISSExtractId, AuditId, CreatedDate, EDWPremiumMasterCalculationPKId, EDWLossMasterCalculationPKId, TypeBureauCode, BureauLineOfInsurance, BureauCompanyNumber, StateProvinceCode, PremiumMasterRunDate, LossMasterRunDate, PolicyKey, PremiumMasterClassCode, LossMasterClassCode, ClaimNumber, ClaimantNumber, RiskTerritoryCode, PolicyEffectiveDate, CauseOfLoss, DeductibleAmount, CoverageCode, SublineCode, PackageModificationAdjustmentGroupDescription, PremiumMasterDirectWrittenPremiumAmount, PaidLossAmount, OutstandingLossAmount, PolicyExpirationDate, InceptionToDatePaidLossAmount, ClaimantCoverageDetailId, AnnualStatementLineNumber, ZipPostalCode, DeductibleIndicatorCode, PolicyLowerLimit, PolicyUpperLimit, TerminalZoneCode, WrittenExposure, PaidAllocatedLossAdjustmentExpenseAmount, OutstandingAllocatedLossAdjustmentExpenseAmount, ClaimLossDate, TransactionEffectiveDate, CoverageGroupCode)\n\tSELECT \n\tFILENAME, \n\tWORKISSEXTRACTID, \n\tAUDITID, \n\tCREATEDDATE, \n\tEDWPREMIUMMASTERCALCULATIONPKID, \n\tEDWLOSSMASTERCALCULATIONPKID, \n\tTYPEBUREAUCODE, \n\tBUREAULINEOFINSURANCE, \n\tBUREAUCOMPANYNUMBER, \n\tSTATEPROVINCECODE, \n\tPREMIUMMASTERRUNDATE, \n\tLOSSMASTERRUNDATE, \n\tPOLICYKEY, \n\tPREMIUMMASTERCLASSCODE, \n\tLOSSMASTERCLASSCODE, \n\tCLAIMNUMBER, \n\tCLAIMANTNUMBER, \n\tRISKTERRITORYCODE, \n\tPOLICYEFFECTIVEDATE, \n\tCAUSEOFLOSS, \n\tDEDUCTIBLEAMOUNT, \n\tCOVERAGECODE, \n\tSUBLINECODE, \n\tPACKAGEMODIFICATIONADJUSTMENTGROUPDESCRIPTION, \n\tPREMIUMMASTERDIRECTWRITTENPREMIUMAMOUNT, \n\tPAIDLOSSAMOUNT, \n\tOUTSTANDINGLOSSAMOUNT, \n\tPOLICYEXPIRATIONDATE, \n\tINCEPTIONTODATEPAIDLOSSAMOUNT, \n\tCLAIMANTCOVERAGEDETAILID, \n\tANNUALSTATEMENTLINENUMBER, \n\tZIPPOSTALCODE, \n\tDEDUCTIBLEINDICATORCODE, \n\tPOLICYLOWERLIMIT, \n\tPOLICYUPPERLIMIT, \n\tTERMINALZONECODE, \n\tWRITTENEXPOSURE, \n\tPAIDALLOCATEDLOSSADJUSTMENTEXPENSEAMOUNT, \n\tOUTSTANDINGALLOCATEDLOSSADJUSTMENTEXPENSEAMOUNT, \n\tCLAIMLOSSDATE, \n\tTRANSACTIONEFFECTIVEDATE, \n\tCOVERAGEGROUPCODE\n\tFROM SRT_ISSFlatFile_Auto_CL\n),\nEXP_Target_PL AS (\n\tSELECT\n\t-- *INF*: TRUNC(SYSDATE,'DD')\n\tCAST(TRUNC(CURRENT_TIMESTAMP, 'DAY') AS TIMESTAMP_NTZ(0)) AS v_RunDate,\n\t-- *INF*: 'ISS_Auto_PL_'||TO_CHAR(v_RunDate,'YYYYMMDD')||'.CSV'\n\t'ISS_Auto_PL_' || TO_CHAR(v_RunDate, 'YYYYMMDD') || '.CSV' AS FileName,\n\tWorkISSExtractId,\n\tAuditId,\n\tCreatedDate,\n\tEDWPremiumMasterCalculationPKId,\n\tEDWLossMasterCalculationPKId,\n\tTypeBureauCode,\n\tBureauLineOfInsurance,\n\tBureauCompanyNumber,\n\tStateProvinceCode,\n\tPremiumMasterRunDate,\n\tLossMasterRunDate,\n\tPolicyKey,\n\tPremiumMasterClassCode,\n\tLossMasterClassCode,\n\tClaimNumber,\n\tClaimantNumber,\n\tRiskTerritoryCode,\n\tPolicyEffectiveDate,\n\tCauseOfLoss,\n\tDeductibleAmount,\n\tCoverageCode,\n\tConstructionCode,\n\tISOFireProtectionCode,\n\tSublineCode,\n\tPackageModificationAdjustmentGroupDescription,\n\tPolicyForm,\n\tPremiumMasterDirectWrittenPremiumAmount,\n\tPaidLossAmount,\n\tOutstandingLossAmount,\n\tPolicyExpirationDate,\n\tInceptionToDatePaidLossAmount,\n\tClaimantCoverageDetailId,\n\tAnnualStatementLineNumber,\n\tZipPostalCode,\n\tDeductibleIndicatorCode,\n\tVehicleModelYear,\n\tDefensiveDriverCode,\n\tPolicyLowerLimit,\n\tPolicyUpperLimit,\n\tTerminalZoneCode,\n\tWrittenExposure,\n\tPaidAllocatedLossAdjustmentExpenseAmount,\n\tOutstandingAllocatedLossAdjustmentExpenseAmount,\n\tClaimLossDate,\n\tTransactionEffectiveDate,\n\tCoverageGroupCode\n\tFROM RTR_CL_PL_PL\n),\nSRT_ISSFlatFILE_Auto_PL AS (\n\tSELECT\n\tFileName, \n\tWorkISSExtractId, \n\tAuditId, \n\tCreatedDate, \n\tEDWPremiumMasterCalculationPKId, \n\tEDWLossMasterCalculationPKId, \n\tTypeBureauCode, \n\tBureauLineOfInsurance, \n\tBureauCompanyNumber, \n\tStateProvinceCode, \n\tPremiumMasterRunDate, \n\tLossMasterRunDate, \n\tPolicyKey, \n\tPremiumMasterClassCode, \n\tLossMasterClassCode, \n\tClaimNumber, \n\tClaimantNumber, \n\tRiskTerritoryCode, \n\tPolicyEffectiveDate, \n\tCauseOfLoss, \n\tDeductibleAmount, \n\tCoverageCode, \n\tSublineCode, \n\tPackageModificationAdjustmentGroupDescription, \n\tPremiumMasterDirectWrittenPremiumAmount, \n\tPaidLossAmount, \n\tOutstandingLossAmount, \n\tPolicyExpirationDate, \n\tInceptionToDatePaidLossAmount, \n\tClaimantCoverageDetailId, \n\tAnnualStatementLineNumber, \n\tZipPostalCode, \n\tDeductibleIndicatorCode, \n\tPolicyLowerLimit, \n\tPolicyUpperLimit, \n\tTerminalZoneCode, \n\tWrittenExposure, \n\tPaidAllocatedLossAdjustmentExpenseAmount, \n\tOutstandingAllocatedLossAdjustmentExpenseAmount, \n\tClaimLossDate, \n\tTransactionEffectiveDate, \n\tCoverageGroupCode\n\tFROM EXP_Target_PL\n\tORDER BY PolicyKey ASC, PremiumMasterClassCode ASC, CoverageCode ASC, AnnualStatementLineNumber ASC, ZipPostalCode ASC\n),\nISSFlatFile_Auto_PL AS (\n\tINSERT INTO ISSFlatFile_Auto\n\t(FileName, WorkISSExtractId, AuditId, CreatedDate, EDWPremiumMasterCalculationPKId, EDWLossMasterCalculationPKId, TypeBureauCode, BureauLineOfInsurance, BureauCompanyNumber, StateProvinceCode, PremiumMasterRunDate, LossMasterRunDate, PolicyKey, PremiumMasterClassCode, LossMasterClassCode, ClaimNumber, ClaimantNumber, RiskTerritoryCode, PolicyEffectiveDate, CauseOfLoss, DeductibleAmount, CoverageCode, SublineCode, PackageModificationAdjustmentGroupDescription, PremiumMasterDirectWrittenPremiumAmount, PaidLossAmount, OutstandingLossAmount, PolicyExpirationDate, InceptionToDatePaidLossAmount, ClaimantCoverageDetailId, AnnualStatementLineNumber, ZipPostalCode, DeductibleIndicatorCode, PolicyLowerLimit, PolicyUpperLimit, TerminalZoneCode, WrittenExposure, PaidAllocatedLossAdjustmentExpenseAmount, OutstandingAllocatedLossAdjustmentExpenseAmount, ClaimLossDate, TransactionEffectiveDate, CoverageGroupCode)\n\tSELECT \n\tFILENAME, \n\tWORKISSEXTRACTID, \n\tAUDITID, \n\tCREATEDDATE, \n\tEDWPREMIUMMASTERCALCULATIONPKID, \n\tEDWLOSSMASTERCALCULATIONPKID, \n\tTYPEBUREAUCODE, \n\tBUREAULINEOFINSURANCE, \n\tBUREAUCOMPANYNUMBER, \n\tSTATEPROVINCECODE, \n\tPREMIUMMASTERRUNDATE, \n\tLOSSMASTERRUNDATE, \n\tPOLICYKEY, \n\tPREMIUMMASTERCLASSCODE, \n\tLOSSMASTERCLASSCODE, \n\tCLAIMNUMBER, \n\tCLAIMANTNUMBER, \n\tRISKTERRITORYCODE, \n\tPOLICYEFFECTIVEDATE, \n\tCAUSEOFLOSS, \n\tDEDUCTIBLEAMOUNT, \n\tCOVERAGECODE, \n\tSUBLINECODE, \n\tPACKAGEMODIFICATIONADJUSTMENTGROUPDESCRIPTION, \n\tPREMIUMMASTERDIRECTWRITTENPREMIUMAMOUNT, \n\tPAIDLOSSAMOUNT, \n\tOUTSTANDINGLOSSAMOUNT, \n\tPOLICYEXPIRATIONDATE, \n\tINCEPTIONTODATEPAIDLOSSAMOUNT, \n\tCLAIMANTCOVERAGEDETAILID, \n\tANNUALSTATEMENTLINENUMBER, \n\tZIPPOSTALCODE, \n\tDEDUCTIBLEINDICATORCODE, \n\tPOLICYLOWERLIMIT, \n\tPOLICYUPPERLIMIT, \n\tTERMINALZONECODE, \n\tWRITTENEXPOSURE, \n\tPAIDALLOCATEDLOSSADJUSTMENTEXPENSEAMOUNT, \n\tOUTSTANDINGALLOCATEDLOSSADJUSTMENTEXPENSEAMOUNT, \n\tCLAIMLOSSDATE, \n\tTRANSACTIONEFFECTIVEDATE, \n\tCOVERAGEGROUPCODE\n\tFROM SRT_ISSFlatFILE_Auto_PL\n),"
                        }
                    ]
                },
                "state": "Inactive",
                "onInactiveMarkAs": "Succeeded"
            }
        ],
        "parameters": {
            "WHERE_CLAUSE": {
                "type": "string",
                "defaultValue": "Default Value"
            }
        },
        "folder": {
            "name": "DataFeed -Informatica/PolicyDataServices/"
        },
        "annotations": []
    }
}